target_approximation/__init__.py
target_approximation/core.py
target_approximation/filter.py
target_approximation/target.py
target_approximation/utils.py
target_approximation/tensortract/__init__.py
target_approximation/tensortract/core.py
target_approximation/tensortract/utils.py
target_approximation/vocaltractlab/__init__.py
target_approximation/vocaltractlab/core.py
target_approximation/vocaltractlab/utils.py
target_approximation-0.0.5.dist-info/licenses/LICENSE
target_approximation-0.0.5.dist-info/METADATA
target_approximation-0.0.5.dist-info/WHEEL
target_approximation-0.0.5.dist-info/top_level.txt
target_approximation-0.0.5.dist-info/RECORD
