Metadata-Version: 2.4
Name: target-approximation
Version: 0.0.5
Summary: Python implementation of the Target-Approximation-Model.
Home-page: https://github.com/paul-krug/target-approximation
Author: Paul Krug
License: MIT
License-File: LICENSE
Requires-Dist: matplotlib
Requires-Dist: numpy
Requires-Dist: pandas
Requires-Dist: resampy
Requires-Dist: scipy
Requires-Dist: tools-io
Dynamic: author
Dynamic: description
Dynamic: description-content-type
Dynamic: home-page
Dynamic: license
Dynamic: license-file
Dynamic: requires-dist
Dynamic: summary
